oa_pynput/__init__.py
oa_pynput/_info.py
oa_pynput/_util/__init__.py
oa_pynput/_util/darwin.py
oa_pynput/_util/darwin_vks.py
oa_pynput/_util/uinput.py
oa_pynput/_util/win32.py
oa_pynput/_util/win32_vks.py
oa_pynput/_util/xorg.py
oa_pynput/_util/xorg_keysyms.py
oa_pynput/keyboard/__init__.py
oa_pynput/keyboard/_base.py
oa_pynput/keyboard/_darwin.py
oa_pynput/keyboard/_dummy.py
oa_pynput/keyboard/_uinput.py
oa_pynput/keyboard/_win32.py
oa_pynput/keyboard/_xorg.py
oa_pynput/mouse/__init__.py
oa_pynput/mouse/_base.py
oa_pynput/mouse/_darwin.py
oa_pynput/mouse/_dummy.py
oa_pynput/mouse/_win32.py
oa_pynput/mouse/_xorg.py
oa_pynput-1.7.7.dist-info/COPYING.LGPL
oa_pynput-1.7.7.dist-info/METADATA
oa_pynput-1.7.7.dist-info/WHEEL
oa_pynput-1.7.7.dist-info/top_level.txt
oa_pynput-1.7.7.dist-info/zip-safe
oa_pynput-1.7.7.dist-info/RECORD
